{
  "gyms": [
    {
      "name": "VioletGym",
      "trainers": [
        {
          "name": "BirdKeeperMatt",
          "pokemon": [
            {
              "name": "FEAROW",
              "item": "SHARP_BEAK",
              "move1": "DRILL_PECK",
              "move2": "HYPER_BEAM",
              "move3": "STEEL_WING",
              "move4": "DOUBLE_EDGE"
            },
            {
              "name": "AERODACTYL",
              "item": "FOCUS_BAND",
              "move1": "ROCK_SLIDE",
              "move2": "WING_ATTACK",
              "move3": "DOUBLE_EDGE",
              "move4": "EARTHQUAKE"
            },
            {
              "name": "CHARIZARD",
              "item": "SCOPE_LENS",
              "move1": "FLAMETHROWER",
              "move2": "WING_ATTACK",
              "move3": "SLASH",
              "move4": "EARTHQUAKE"
            },
            {
              "name": "NIDOKING",
              "item": "BLACKBELT",
              "move1": "EARTHQUAKE",
              "move2": "THUNDERBOLT",
              "move3": "FIRE_BLAST",
              "move4": "ROCK_SLIDE"
            },
            {
              "name": "PILOSWINE",
              "item": "NEVERMELTICE",
              "move1": "ICE_BEAM",
              "move2": "EARTHQUAKE",
              "move3": "BODY_SLAM",
              "move4": "DOUBLE_EDGE"
            },
            {
              "name": "MACHAMP",
              "item": "BLACKGLASSES",
              "move1": "CROSS_CHOP",
              "move2": "ROCK_SLIDE",
              "move3": "EARTHQUAKE",
              "move4": "STRENGTH"
            }
          ]
        },
        {
          "name": "LeaderFalkner",
          "pokemon": [
            {
              "name": "ZAPDOS",
              "item": "SCOPE_LENS",
              "move1": "THUNDERBOLT",
              "move2": "DRILL_PECK",
              "move3": "THUNDER",
              "move4": "AGILITY"
            },
            {
              "name": "ARTICUNO",
              "item": "NEVERMELTICE",
              "move1": "ICE_BEAM",
              "move2": "FLY",
              "move3": "REFLECT",
              "move4": "HYPER_BEAM"
            },
            {
              "name": "MOLTRES",
              "item": "CHARCOAL",
              "move1": "FIRE_BLAST",
              "move2": "FLY",
              "move3": "TOXIC",
              "move4": "REST"
            },
            {
              "name": "PIDGEOT",
              "item": "BRIGHTPOWDER",
              "move1": "DOUBLE_EDGE",
              "move2": "HYPER_BEAM",
              "move3": "FLY",
              "move4": "MIRROR_MOVE"
            },
            {
              "name": "STEELIX",
              "item": "METAL_COAT",
              "move1": "EARTHQUAKE",
              "move2": "ROCK_SLIDE",
              "move3": "CURSE",
              "move4": "IRON_TAIL"
            },
            {
              "name": "QUAGSIRE",
              "item": "LEFTOVERS",
              "move1": "SURF",
              "move2": "EARTHQUAKE",
              "move3": "AMNESIA",
              "move4": "ICE_BEAM"
            }
          ]
        }
      ]
    },
    {
      "name": "AzaleaGym",
      "trainers": [
        {
          "name": "BugCatcherChaz",
          "pokemon": [
            {
              "name": "BEEDRILL",
              "item": "BITTER_BERRY",
              "move1": "SWORDS_DANCE",
              "move2": "DOUBLE_EDGE",
              "move3": "SLUDGE_BOMB",
              "move4": "TWINEEDLE"
            },
            {
              "name": "BUTTERFREE",
              "item": "PRZCUREBERRY",
              "move1": "SLEEP_POWDER",
              "move2": "PSYCHIC",
              "move3": "GIGA_DRAIN",
              "move4": "STUN_SPORE"
            },
            {
              "name": "SANDSLASH",
              "item": "SCOPE_LENS",
              "move1": "DYNAMIC_PUNCH",
              "move2": "EARTHQUAKE",
              "move3": "ROCK_SLIDE",
              "move4": "METAL_CLAW"
            },
            {
              "name": "LANTURN",
              "item": "QUICK_CLAW",
              "move1": "SURF",
              "move2": "TOXIC",
              "move3": "CONFUSE_RAY",
              "move4": "THUNDERBOLT"
            },
            {
              "name": "GOLEM",
              "item": "FOCUS_BAND",
              "move1": "EXPLOSION",
              "move2": "MAGNITUDE",
              "move3": "ROCK_SLIDE",
              "move4": "STRENGTH"
            },
            {
              "name": "ALAKAZAM",
              "item": "KINGS_ROCK",
              "move1": "PSYCHIC",
              "move2": "THUNDER_PUNCH",
              "move3": "FIRE_PUNCH",
              "move4": "FUTURE_SIGHT"
            }
          ]
        },
        {
          "name": "TwinsMinAndLyn",
          "pokemon": [
            {
              "name": "SCYTHER",
              "item": "KINGS_ROCK",
              "move1": "WING_ATTACK",
              "move2": "STEEL_WING",
              "move3": "REVERSAL",
              "move4": "HYPER_BEAM"
            },
            {
              "name": "PINSIR",
              "item": "SCOPE_LENS",
              "move1": "FURY_CUTTER",
              "move2": "SUBMISSION",
              "move3": "BODY_SLAM",
              "move4": "SEISMIC_TOSS"
            },
            {
              "name": "PARASECT",
              "item": "BRIGHTPOWDER",
              "move1": "GIGA_DRAIN",
              "move2": "SLUDGE_BOMB",
              "move3": "SWAGGER",
              "move4": "STUN_SPORE"
            },
            {
              "name": "DONPHAN",
              "item": "QUICK_CLAW",
              "move1": "EARTHQUAKE",
              "move2": "ANCIENT_POWER",
              "move3": "DOUBLE_EDGE",
              "move4": "FLAIL"
            },
            {
              "name": "NIDOQUEEN",
              "item": "LEFTOVERS",
              "move1": "EARTHQUAKE",
              "move2": "SURF",
              "move3": "THUNDER",
              "move4": "RAIN_DANCE"
            },
            {
              "name": "KINGDRA",
              "item": "FOCUS_BAND",
              "move1": "DRAGON_BREATH",
              "move2": "HYDRO_PUMP",
              "move3": "RETURN",
              "move4": "ICE_BEAM"
            }
          ]
        },
        {
          "name": "LeaderBugsy",
          "pokemon": [
            {
              "name": "HERACROSS",
              "item": "FOCUS_BAND",
              "move1": "MEGAHORN",
              "move2": "REVERSAL",
              "move3": "TAKE_DOWN",
              "move4": "EARTHQUAKE"
            },
            {
              "name": "SCIZOR",
              "item": "KINGS_ROCK",
              "move1": "METAL_CLAW",
              "move2": "REVERSAL",
              "move3": "WING_ATTACK",
              "move4": "SLASH"
            },
            {
              "name": "LUGIA",
              "item": "LEFTOVERS",
              "move1": "AEROBLAST",
              "move2": "EARTHQUAKE",
              "move3": "PSYCHIC",
              "move4": "SAFEGUARD"
            },
            {
              "name": "SLOWKING",
              "item": "QUICK_CLAW",
              "move1": "PSYCHIC",
              "move2": "SURF",
              "move3": "EARTHQUAKE",
              "move4": "FUTURE_SIGHT"
            },
            {
              "name": "TYRANITAR",
              "item": "QUICK_CLAW",
              "move1": "CRUNCH",
              "move2": "ROCK_SLIDE",
              "move3": "EARTHQUAKE",
              "move4": "HYPER_BEAM"
            },
            {
              "name": "JOLTEON",
              "item": "KINGS_ROCK",
              "move1": "THUNDERBOLT",
              "move2": "HIDDEN_POWER",
              "move3": "ROAR",
              "move4": "THUNDER_WAVE"
            }
          ]
        }
      ]
    },
    {
      "name": "GoldenrodGym",
      "trainers": [
        {
          "name": "LassLois",
          "pokemon": [
            {
              "name": "GRANBULL",
              "item": "PRZCUREBERRY",
              "move1": "STRENGTH",
              "move2": "SHADOW_BALL",
              "move3": "SLUDGE_BOMB",
              "move4": "DYNAMIC_PUNCH"
            },
            {
              "name": "DODRIO",
              "item": "MAGNET",
              "move1": "MUD_SLAP",
              "move2": "TRI_ATTACK",
              "move3": "DRILL_PECK",
              "move4": "SKY_ATTACK"
            },
            {
              "name": "ESPEON",
              "item": "KINGS_ROCK",
              "move1": "PSYCHIC",
              "move2": "BITE",
              "move3": "REFLECT",
              "move4": "HIDDEN_POWER"
            },
            {
              "name": "RAICHU",
              "item": "FOCUS_BAND",
              "move1": "THUNDERBOLT",
              "move2": "THUNDER_WAVE",
              "move3": "REVERSAL",
              "move4": "SURF"
            },
            {
              "name": "CORSOLA",
              "item": "LEFTOVERS",
              "move1": "SURF",
              "move2": "ROCK_SLIDE",
              "move3": "PSYCHIC",
              "move4": "MIRROR_COAT"
            },
            {
              "name": "GENGAR",
              "item": "SCOPE_LENS",
              "move1": "PSYCHIC",
              "move2": "ICE_PUNCH",
              "move3": "FIRE_PUNCH",
              "move4": "THUNDERBOLT"
            }
          ]
        },
        {
          "name": "BeautyRita",
          "pokemon": [
            {
              "name": "URSARING",
              "item": "QUICK_CLAW",
              "move1": "DYNAMIC_PUNCH",
              "move2": "SLASH",
              "move3": "EARTHQUAKE",
              "move4": "CRUNCH"
            },
            {
              "name": "RATICATE",
              "item": "MAGNET",
              "move1": "HYPER_FANG",
              "move2": "SUPER_FANG",
              "move3": "REVERSAL",
              "move4": "ROAR"
            },
            {
              "name": "TAUROS",
              "item": "FOCUS_BAND",
              "move1": "STOMP",
              "move2": "EARTHQUAKE",
              "move3": "IRON_TAIL",
              "move4": "SCARY_FACE"
            },
            {
              "name": "HYPNO",
              "item": "PRZCUREBERRY",
              "move1": "DYNAMIC_PUNCH",
              "move2": "PSYCHIC",
              "move3": "SHADOW_BALL",
              "move4": "LIGHT_SCREEN"
            },
            {
              "name": "RAPIDASH",
              "item": "KINGS_ROCK",
              "move1": "FLAMETHROWER",
              "move2": "DOUBLE_KICK",
              "move3": "STOMP",
              "move4": "IRON_TAIL"
            },
            {
              "name": "AMPHAROS",
              "item": "SCOPE_LENS",
              "move1": "THUNDERBOLT",
              "move2": "THUNDER_WAVE",
              "move3": "FIRE_PUNCH",
              "move4": "BODY_SLAM"
            }
          ]
        },
        {
          "name": "LeaderWhitney",
          "pokemon": [
            {
              "name": "MILTANK",
              "item": "KINGS_ROCK",
              "move1": "STOMP",
              "move2": "EARTHQUAKE",
              "move3": "REVERSAL",
              "move4": "MILK_DRINK"
            },
            {
              "name": "SNORLAX",
              "item": "SCOPE_LENS",
              "move1": "BODY_SLAM",
              "move2": "EARTHQUAKE",
              "move3": "SHADOW_BALL",
              "move4": "HIDDEN_POWER"
            },
            {
              "name": "GOLDUCK",
              "item": "BRIGHTPOWDER",
              "move1": "SURF",
              "move2": "PSYCHIC",
              "move3": "ICE_BEAM",
              "move4": "CROSS_CHOP"
            },
            {
              "name": "DONPHAN",
              "item": "QUICK_CLAW",
              "move1": "EARTHQUAKE",
              "move2": "ANCIENT_POWER",
              "move3": "DOUBLE_EDGE",
              "move4": "FLAIL"
            },
            {
              "name": "CELEBI",
              "item": "LEFTOVERS",
              "move1": "PSYCHIC",
              "move2": "GIGA_DRAIN",
              "move3": "RECOVER",
              "move4": "LEECH_SEED"
            },
            {
              "name": "DRAGONITE",
              "item": "MAGNET",
              "move1": "FLY",
              "move2": "BODY_SLAM",
              "move3": "THUNDER_WAVE",
              "move4": "HIDDEN_POWER"
            }
          ]
        }
      ]
    },
    {
      "name": "EcruteakGym",
      "trainers": [
        {
          "name": "MediumHolly",
          "pokemon": [
            {
              "name": "MISDREAVUS",
              "item": "MYSTERYBERRY",
              "move1": "MEAN_LOOK",
              "move2": "PERISH_SONG",
              "move3": "PAIN_SPLIT",
              "move4": "PSYCHIC"
            },
            {
              "name": "PINSIR",
              "item": "SCOPE_LENS",
              "move1": "FURY_CUTTER",
              "move2": "SUBMISSION",
              "move3": "BODY_SLAM",
              "move4": "SEISMIC_TOSS"
            },
            {
              "name": "ENTEI",
              "item": "QUICK_CLAW",
              "move1": "FIRE_BLAST",
              "move2": "EARTHQUAKE",
              "move3": "IRON_TAIL",
              "move4": "GIGA_DRAIN"
            },
            {
              "name": "TENTACRUEL",
              "item": "FOCUS_BAND",
              "move1": "SURF",
              "move2": "ICE_BEAM",
              "move3": "REFLECT",
              "move4": "MIRROR_COAT"
            },
            {
              "name": "VICTREEBEL",
              "item": "MAGNET",
              "move1": "RAZOR_LEAF",
              "move2": "SLUDGE_BOMB",
              "move3": "BODY_SLAM",
              "move4": "STUN_SPORE"
            },
            {
              "name": "KANGASKHAN",
              "item": "BRIGHTPOWDER",
              "move1": "SUBMISSION",
              "move2": "EARTHQUAKE",
              "move3": "ROCK_SLIDE",
              "move4": "HYPER_BEAM"
            }
          ]
        },
        {
          "name": "SageTy",
          "pokemon": [
            {
              "name": "HAUNTER",
              "item": "PRZCUREBERRY",
              "move1": "SHADOW_BALL",
              "move2": "PSYCHIC",
              "move3": "GIGA_DRAIN",
              "move4": "DESTINY_BOND"
            },
            {
              "name": "AERODACTYL",
              "item": "KINGS_ROCK",
              "move1": "ANCIENT_POWER",
              "move2": "WING_ATTACK",
              "move3": "EARTHQUAKE",
              "move4": "HYPER_BEAM"
            },
            {
              "name": "JYNX",
              "item": "ICE_BERRY",
              "move1": "ICE_BEAM",
              "move2": "PSYCHIC",
              "move3": "DYNAMIC_PUNCH",
              "move4": "SHADOW_BALL"
            },
            {
              "name": "UMBREON",
              "item": "FOCUS_BAND",
              "move1": "SWAGGER",
              "move2": "SCREECH",
              "move3": "FEINT_ATTACK",
              "move4": "PSYCHIC"
            },
            {
              "name": "MUK",
              "item": "BURNT_BERRY",
              "move1": "SLUDGE_BOMB",
              "move2": "MEAN_LOOK",
              "move3": "ZAP_CANNON",
              "move4": "ICE_PUNCH"
            },
            {
              "name": "SUICUNE",
              "item": "BRIGHTPOWDER",
              "move1": "SURF",
              "move2": "ICE_BEAM",
              "move3": "ROAR",
              "move4": "HIDDEN_POWER"
            }
          ]
        },
        {
          "name": "LeaderMorty",
          "pokemon": [
            {
              "name": "GENGAR",
              "item": "KINGS_ROCK",
              "move1": "PSYCHIC",
              "move2": "THUNDERBOLT",
              "move3": "FIRE_PUNCH",
              "move4": "CONFUSE_RAY"
            },
            {
              "name": "RAIKOU",
              "item": "FOCUS_BAND",
              "move1": "THUNDERBOLT",
              "move2": "BITE",
              "move3": "IRON_TAIL",
              "move4": "HIDDEN_POWER"
            },
            {
              "name": "ARCANINE",
              "item": "MAGNET",
              "move1": "FLAMETHROWER",
              "move2": "EXTREME_SPEED",
              "move3": "CRUNCH",
              "move4": "HYPER_BEAM"
            },
            {
              "name": "LAPRAS",
              "item": "LEFTOVERS",
              "move1": "SURF",
              "move2": "ICE_BEAM",
              "move3": "THUNDERBOLT",
              "move4": "BODY_SLAM"
            },
            {
              "name": "TYRANITAR",
              "item": "QUICK_CLAW",
              "move1": "CRUNCH",
              "move2": "ROCK_SLIDE",
              "move3": "EARTHQUAKE",
              "move4": "HYPER_BEAM"
            },
            {
              "name": "HO-OH",
              "item": "MINT_BERRY",
              "move1": "SACRED_FIRE",
              "move2": "THUNDER",
              "move3": "EARTHQUAKE",
              "move4": "GIGA_DRAIN"
            }
          ]
        }
      ]
    },
    {
      "name": "Cianwood Gym",
      "trainers": [
        {
          "name": "BlackBeltNick",
          "pokemon": [
            {
              "name": "MACHOKE",
              "item": "MINT BERRY",
              "move1": "FISSURE",
              "move2": "ROCK_SLIDE",
              "move3": "REST",
              "move4": "SLEEP_TALK"
            },
            {
              "name": "GRAVELER",
              "item": "NONE",
              "move1": "FISSURE",
              "move2": "ROCK_SLIDE",
              "move3": "REST",
              "move4": "SLEEP_TALK"
            },
            {
              "name": "KINGLER",
              "item": "MYSTERYBERRY",
              "move1": "GUILLOTINE",
              "move2": "CRABHAMMER",
              "move3": "REST",
              "move4": "SLEEP_TALK"
            },
            {
              "name": "ARBOK",
              "item": "PRZCUREBERRY",
              "move1": "FISSURE",
              "move2": "ROCK_SLIDE",
              "move3": "REST",
              "move4": "SLEEP_TALK"
            },
            {
              "name": "DRAGONAIR",
              "item": "DRAGON SCALE",
              "move1": "HORN_DRILL",
              "move2": "DRAGON_BREATH",
              "move3": "REST",
              "move4": "SLEEP_TALK"
            },
            {
              "name": "PINSIR",
              "item": "BITTER BERRY",
              "move1": "GUILLOTINE",
              "move2": "FURY_CUTTER",
              "move3": "REST",
              "move4": "SLEEP_TALK"
            }
          ]
        },
        {
          "name": "LeaderChuck",
          "pokemon": [
            {
              "name": "POLIWRATH",
              "item": "MINT BERRY",
              "move1": "DYNAMIC_PUNCH",
              "move2": "BELLY_DRUM",
              "move3": "REST",
              "move4": "SLEEP_TALK"
            },
            {
              "name": "SANDSLASH",
              "item": "SCOPE LENS",
              "move1": "DYNAMIC_PUNCH",
              "move2": "EARTHQUAKE",
              "move3": "ROCK_SLIDE",
              "move4": "METAL_CLAW"
            },
            {
              "name": "URSARING",
              "item": "QUICK CLAW",
              "move1": "DYNAMIC_PUNCH",
              "move2": "SLASH",
              "move3": "EARTHQUAKE",
              "move4": "CRUNCH"
            },
            {
              "name": "AMPHAROS",
              "item": "BRIGHTPOWDER",
              "move1": "DYNAMIC_PUNCH",
              "move2": "THUNDERBOLT",
              "move3": "FIRE_PUNCH",
              "move4": "LIGHT_SCREEN"
            },
            {
              "name": "HITMONCHAN",
              "item": "KING\u0027S ROCK",
              "move1": "DYNAMIC_PUNCH",
              "move2": "MEGA_PUNCH",
              "move3": "MACH_PUNCH",
              "move4": "PURSUIT"
            },
            {
              "name": "HYPNO",
              "item": "PRZCUREBERRY",
              "move1": "DYNAMIC_PUNCH",
              "move2": "PSYCHIC",
              "move3": "SHADOW_BALL",
              "move4": "LIGHT_SCREEN"
            }
          ]
        }
      ]
    },
    {
      "name": "OlivineGym",
      "trainers": [
        {
          "name": "LeaderJasmine",
          "pokemon": [
            {
              "name": "STEELIX",
              "item": "QUICK CLAW",
              "move1": "IRON_TAIL",
              "move2": "EARTHQUAKE",
              "move3": "ROCK_SLIDE",
              "move4": "RETURN"
            },
            {
              "name": "STANTLER",
              "item": "PRZCUREBERRY",
              "move1": "PSYCHIC",
              "move2": "EARTHQUAKE",
              "move3": "LIGHT_SCREEN",
              "move4": "ROAR"
            },
            {
              "name": "BLASTOISE",
              "item": "MAGNET",
              "move1": "SURF",
              "move2": "EARTHQUAKE",
              "move3": "ICE_BEAM",
              "move4": "MIRROR_COAT"
            },
            {
              "name": "SLOWBRO",
              "item": "BRIGHTPOWDER",
              "move1": "SURF",
              "move2": "PSYCHIC",
              "move3": "EARTHQUAKE",
              "move4": "ICE_BEAM"
            },
            {
              "name": "RAPIDASH",
              "item": "KING\u0027S ROCK",
              "move1": "FLAMETHROWER",
              "move2": "DOUBLE_KICK",
              "move3": "STOMP",
              "move4": "IRON_TAIL"
            },
            {
              "name": "SCIZOR",
              "item": "FOCUS BAND",
              "move1": "METAL_CLAW",
              "move2": "REVERSAL",
              "move3": "WING_ATTACK",
              "move4": "SLASH"
            }
          ]
        }
      ]
    },
    {
      "name": "TeamRocketInterruption",
      "trainers": [
        {
          "name": "RocketGruntMale",
          "pokemon": [
            {
              "name": "WEEZING",
              "item": "BITTER BERRY",
              "move1": "EXPLOSION",
              "move2": "SLUDGE",
              "move3": "PSYBEAM",
              "move4": "SCREECH"
            },
            {
              "name": "ELECTRODE",
              "item": "MINT BERRY",
              "move1": "EXPLOSION",
              "move2": "THUNDERBOLT",
              "move3": "MIRROR_COAT",
              "move4": "SCREECH"
            },
            {
              "name": "CLOYSTER",
              "item": "NONE",
              "move1": "EXPLOSION",
              "move2": "ICE_BEAM",
              "move3": "SURF",
              "move4": "SCREECH"
            },
            {
              "name": "SUDOWOODO",
              "item": "PRZCUREBERRY",
              "move1": "SELF_DESTRUCT",
              "move2": "ROCK_SLIDE",
              "move3": "EARTHQUAKE",
              "move4": "FEINT_ATTACK"
            },
            {
              "name": "FORRETRESS",
              "item": "NONE",
              "move1": "EXPLOSION",
              "move2": "PIN_MISSILE",
              "move3": "GIGA_DRAIN",
              "move4": "DOUBLE_EDGE"
            },
            {
              "name": "GOLEM",
              "item": "FOCUS BAND",
              "move1": "EXPLOSION",
              "move2": "MAGNITUDE",
              "move3": "ROCK_SLIDE",
              "move4": "STRENGTH"
            }
          ]
        },
        {
          "name": "RocketGruntFemale",
          "pokemon": [
            {
              "name": "HOUNDOUR",
              "item": "CHARCOAL",
              "move1": "TOXIC",
              "move2": "FIRE_SPIN",
              "move3": "FLAMETHROWER",
              "move4": "DETECT"
            },
            {
              "name": "SHUCKLE",
              "item": "PSNCUREBERRY",
              "move1": "TOXIC",
              "move2": "WRAP",
              "move3": "DIG",
              "move4": "PROTECT"
            },
            {
              "name": "AZUMARILL",
              "item": "NONE",
              "move1": "PERISH_SONG",
              "move2": "WHIRLPOOL",
              "move3": "SURF",
              "move4": "PROTECT"
            },
            {
              "name": "SHELLDER",
              "item": "MINT BERRY",
              "move1": "TOXIC",
              "move2": "CLAMP",
              "move3": "ICE_BEAM",
              "move4": "PROTECT"
            },
            {
              "name": "ONIX",
              "item": "BITTER BERRY",
              "move1": "TOXIC",
              "move2": "BIND",
              "move3": "EARTHQUAKE",
              "move4": "PROTECT"
            },
            {
              "name": "DEWGONG",
              "item": "PRZCUREBERRY",
              "move1": "PERISH_SONG",
              "move2": "WHIRLPOOL",
              "move3": "AURORA_BEAM",
              "move4": "PROTECT"
            }
          ]
        },
        {
          "name": "RocketExecutiveFemale",
          "pokemon": [
            {
              "name": "VILEPLUME",
              "item": "MAGNET",
              "move1": "RAZOR_LEAF",
              "move2": "SLUDGE_BOMB",
              "move3": "PETAL_DANCE",
              "move4": "FRUSTRATION"
            },
            {
              "name": "ARBOK",
              "item": "NONE",
              "move1": "THIEF",
              "move2": "EARTHQUAKE",
              "move3": "ROCK_SLIDE",
              "move4": "FRUSTRATION"
            },
            {
              "name": "MAGCARGO",
              "item": "MINT BERRY",
              "move1": "FLAMETHROWER",
              "move2": "ROCK_SLIDE",
              "move3": "EARTHQUAKE",
              "move4": "FRUSTRATION"
            },
            {
              "name": "KABUTOPS",
              "item": "BERSERK GENE",
              "move1": "THIEF",
              "move2": "SURF",
              "move3": "ANCIENT_POWER",
              "move4": "FRUSTRATION"
            },
            {
              "name": "VICTREEBEL",
              "item": "PRZCUREBERRY",
              "move1": "RAZOR_LEAF",
              "move2": "SLUDGE_BOMB",
              "move3": "GIGA_DRAIN",
              "move4": "FRUSTRATION"
            },
            {
              "name": "GOLBAT",
              "item": "NONE",
              "move1": "THIEF",
              "move2": "WING_ATTACK",
              "move3": "HAZE",
              "move4": "FRUSTRATION"
            }
          ]
        },
        {
          "name": "RocketExecutiveMale",
          "pokemon": [
            {
              "name": "HOUNDOOM",
              "item": "MAGNET",
              "move1": "CRUNCH",
              "move2": "SUNNY_DAY",
              "move3": "FIRE_BLAST",
              "move4": "SOLAR_BEAM"
            },
            {
              "name": "OCTILLERY",
              "item": "SCOPE LENS",
              "move1": "SURF",
              "move2": "PSYBEAM",
              "move3": "SWAGGER",
              "move4": "SCREECH"
            },
            {
              "name": "WOBBUFFET",
              "item": "FOCUS BAND",
              "move1": "COUNTER",
              "move2": "MIRROR_COAT",
              "move3": "SAFEGUARD",
              "move4": "DESTINY_BOND"
            },
            {
              "name": "HYPNO",
              "item": "PRZCUREBERRY",
              "move1": "PSYCHIC",
              "move2": "SHADOW_BALL",
              "move3": "THUNDER_PUNCH",
              "move4": "SWAGGER"
            },
            {
              "name": "PARASECT",
              "item": "BRIGHTPOWDER",
              "move1": "GIGA_DRAIN",
              "move2": "SLUDGE_BOMB",
              "move3": "SWAGGER",
              "move4": "STUN_SPORE"
            },
            {
              "name": "TYRANITAR",
              "item": "QUICK CLAW",
              "move1": "ROCK_SLIDE",
              "move2": "EARTHQUAKE",
              "move3": "SWAGGER",
              "move4": "SCREECH"
            }
          ]
        }
      ]
    },
    {
      "name": "MahoganyGym",
      "trainers": [
        {
          "name": "BoarderAlvin",
          "pokemon": [
            {
              "name": "SEEL",
              "item": "PRZCUREBERRY",
              "move1": "SURF",
              "move2": "ICE_BEAM",
              "move3": "ENCORE",
              "move4": "DISABLE"
            },
            {
              "name": "KADABRA",
              "item": "MYSTIC WATER",
              "move1": "PSYBEAM",
              "move2": "ICE_PUNCH",
              "move3": "ENCORE",
              "move4": "DISABLE"
            },
            {
              "name": "DELIBIRD",
              "item": "MINT BERRY",
              "move1": "FLY",
              "move2": "BLIZZARD",
              "move3": "QUICK_ATTACK",
              "move4": "RAPID_SPIN"
            },
            {
              "name": "MAGNETON",
              "item": "PSNCUREBERRY",
              "move1": "THUNDERBOLT",
              "move2": "TRI_ATTACK",
              "move3": "ROLLOUT",
              "move4": "MIMIC"
            },
            {
              "name": "VENUSAUR",
              "item": "BITTER BERRY",
              "move1": "RAZOR_LEAF",
              "move2": "BODY_SLAM",
              "move3": "REFLECT",
              "move4": "ROAR"
            },
            {
              "name": "SNEASEL",
              "item": "ICE BERRY",
              "move1": "SLASH",
              "move2": "ICE_BEAM",
              "move3": "SHADOW_BALL",
              "move4": "COUNTER"
            }
          ]
        },
        {
          "name": "SkierCarol",
          "pokemon": [
            {
              "name": "SEADRA",
              "item": "KING\u0027S ROCK",
              "move1": "ICY_WIND",
              "move2": "TWISTER",
              "move3": "HEADBUTT",
              "move4": "BLIZZARD"
            },
            {
              "name": "RATICATE",
              "item": "PRZCUREBERRY",
              "move1": "ICY_WIND",
              "move2": "BITE",
              "move3": "HYPER_FANG",
              "move4": "BLIZZARD"
            },
            {
              "name": "OMASTAR",
              "item": "MINT BERRY",
              "move1": "ICY_WIND",
              "move2": "HEADBUTT",
              "move3": "BITE",
              "move4": "BLIZZARD"
            },
            {
              "name": "MAROWAK",
              "item": "BURNT BERRY",
              "move1": "ICY_WIND",
              "move2": "ROCK_SLIDE",
              "move3": "HEADBUTT",
              "move4": "BLIZZARD"
            },
            {
              "name": "POLIWHIRL",
              "item": "BITTER BERRY",
              "move1": "ICY_WIND",
              "move2": "HEADBUTT",
              "move3": "WHIRLPOOL",
              "move4": "BLIZZARD"
            },
            {
              "name": "PERSIAN",
              "item": "PSNCUREBERRY",
              "move1": "ICY_WIND",
              "move2": "HEADBUTT",
              "move3": "BITE",
              "move4": "ROAR"
            }
          ]
        },
        {
          "name": "LeaderPryce",
          "pokemon": [
            {
              "name": "PILOSWINE",
              "item": "QUICK CLAW",
              "move1": "EARTHQUAKE",
              "move2": "ICE_BEAM",
              "move3": "ANCIENT_POWER",
              "move4": "BODY_SLAM"
            },
            {
              "name": "QUAGSIRE",
              "item": "BRIGHTPOWDER",
              "move1": "SURF",
              "move2": "EARTHQUAKE",
              "move3": "ICE_BEAM",
              "move4": "IRON_TAIL"
            },
            {
              "name": "HITMONTOP",
              "item": "MAGNET",
              "move1": "HIGH_JUMP_KICK",
              "move2": "STRENGTH",
              "move3": "DIG",
              "move4": "COUNTER"
            },
            {
              "name": "TENTACRUEL",
              "item": "FOCUS BAND",
              "move1": "SURF",
              "move2": "ICE_BEAM",
              "move3": "REFLECT",
              "move4": "MIRROR_COAT"
            },
            {
              "name": "GIRAFARIG",
              "item": "PRZCUREBERRY",
              "move1": "HEADBUTT",
              "move2": "PSYCHIC",
              "move3": "EARTHQUAKE",
              "move4": "SHADOW_BALL"
            },
            {
              "name": "ARTICUNO",
              "item": "SCOPE LENS",
              "move1": "ICE_BEAM",
              "move2": "FLY",
              "move3": "DOUBLE_EDGE",
              "move4": "BUBBLE_BEAM"
            }
          ]
        }
      ]
    },
    {
      "name": "Blackthorn Gym",
      "trainers": [
        {
          "name": "CooltrainerGloria",
          "pokemon": [
            {
              "name": "SMEARGLE",
              "item": "FOCUS BAND",
              "move1": "SPIDER_WEB",
              "move2": "SPORE",
              "move3": "NIGHTMARE",
              "move4": "SUPER_FANG"
            },
            {
              "name": "TANGELA",
              "item": "BITTER BERRY",
              "move1": "BIND",
              "move2": "SLEEP_POWDER",
              "move3": "MEGA_DRAIN",
              "move4": "SLUDGE_BOMB"
            },
            {
              "name": "JYNX",
              "item": "ICE BERRY",
              "move1": "MEAN_LOOK",
              "move2": "LOVELY_KISS",
              "move3": "DREAM_EATER",
              "move4": "ICE_PUNCH"
            },
            {
              "name": "GOLDUCK",
              "item": "PRZCUREBERRY",
              "move1": "WHIRLPOOL",
              "move2": "HYPNOSIS",
              "move3": "PSYCHIC",
              "move4": "SUBMISSION"
            },
            {
              "name": "HAUNTER",
              "item": "MINT BERRY",
              "move1": "MEAN_LOOK",
              "move2": "HYPNOSIS",
              "move3": "NIGHTMARE",
              "move4": "NIGHT_SHADE"
            },
            {
              "name": "NINETALES",
              "item": "BURNT BERRY",
              "move1": "FIRE_SPIN",
              "move2": "HYPNOSIS",
              "move3": "FEINT_ATTACK",
              "move4": "FLAMETHROWER"
            }
          ]
        },
        {
          "name": "CooltrainerVince",
          "pokemon": [
            {
              "name": "IVYSAUR",
              "item": "BURNT BERRY",
              "move1": "RAZOR_LEAF",
              "move2": "CUT",
              "move3": "LEECH_SEED",
              "move4": "REFLECT"
            },
            {
              "name": "WARTORTLE",
              "item": "PRZCUREBERRY",
              "move1": "HYDRO_PUMP",
              "move2": "BLIZZARD",
              "move3": "REFLECT",
              "move4": "MIRROR_COAT"
            },
            {
              "name": "CHARMELEON",
              "item": "MINT BERRY",
              "move1": "FIRE_BLAST",
              "move2": "SLASH",
              "move3": "DIG",
              "move4": "COUNTER"
            },
            {
              "name": "BAYLEEF",
              "item": "BITTER BERRY",
              "move1": "RAZOR_LEAF",
              "move2": "BODY_SLAM",
              "move3": "COUNTER",
              "move4": "LIGHT_SCREEN"
            },
            {
              "name": "CROCONAW",
              "item": "NONE",
              "move1": "HYDRO_PUMP",
              "move2": "CRUNCH",
              "move3": "SLASH",
              "move4": "DIG"
            },
            {
              "name": "QUILAVA",
              "item": "PSNCUREBERRY",
              "move1": "FIRE_BLAST",
              "move2": "DIG",
              "move3": "REVERSAL",
              "move4": "ROAR"
            }
          ]
        },
        {
          "name": "LeaderClair",
          "pokemon": [
            {
              "name": "KINGDRA",
              "item": "BRIGHTPOWDER",
              "move1": "DRAGON_BREATH",
              "move2": "HYDRO_PUMP",
              "move3": "RETURN",
              "move4": "ICE_BEAM"
            },
            {
              "name": "AMPHAROS",
              "item": "QUICK CLAW",
              "move1": "THUNDERBOLT",
              "move2": "THUNDER_WAVE",
              "move3": "FIRE_PUNCH",
              "move4": "BODY_SLAM"
            },
            {
              "name": "NIDOKING",
              "item": "SCOPE LENS",
              "move1": "EARTHQUAKE",
              "move2": "DOUBLE_KICK",
              "move3": "SHADOW_BALL",
              "move4": "BODY_SLAM"
            },
            {
              "name": "RHYDON",
              "item": "FOCUS BAND",
              "move1": "ROCK_SLIDE",
              "move2": "EARTHQUAKE",
              "move3": "BODY_SLAM",
              "move4": "ROAR"
            },
            {
              "name": "CHARIZARD",
              "item": "KING\u0027S ROCK",
              "move1": "FLAMETHROWER",
              "move2": "WING_ATTACK",
              "move3": "EARTHQUAKE",
              "move4": "BODY_SLAM"
            },
            {
              "name": "GYARADOS",
              "item": "MAGNET",
              "move1": "WATERFALL",
              "move2": "DOUBLE_EDGE",
              "move3": "ICE_BEAM",
              "move4": "DRAGON_BREATH"
            }
          ]
        }
      ]
    },
    {
      "name": "EliteFour",
      "trainers": [
        {
          "name": "EliteFourWill",
          "pokemon": [
            {
              "name": "XATU",
              "item": "BRIGHTPOWDER",
              "move1": "PSYCHIC",
              "move2": "DRILL_PECK",
              "move3": "GIGA_DRAIN",
              "move4": "FEINT_ATTACK"
            },
            {
              "name": "ELECTABUZZ",
              "item": "KING\u0027S ROCK",
              "move1": "THUNDERBOLT",
              "move2": "PSYCHIC",
              "move3": "ICE_PUNCH",
              "move4": "ROLLING_KICK"
            },
            {
              "name": "MANTINE",
              "item": "MAGNET",
              "move1": "WATERFALL",
              "move2": "WING_ATTACK",
              "move3": "ICE_BEAM",
              "move4": "HAZE"
            },
            {
              "name": "FLAREON",
              "item": "QUICK CLAW",
              "move1": "FIRE_BLAST",
              "move2": "BODY_SLAM",
              "move3": "SHADOW_BALL",
              "move4": "ROAR"
            },
            {
              "name": "CHANSEY",
              "item": "FOCUS BAND",
              "move1": "PSYCHIC",
              "move2": "ICE_BEAM",
              "move3": "THUNDERBOLT",
              "move4": "COUNTER"
            },
            {
              "name": "HYPNO",
              "item": "SCOPE LENS",
              "move1": "PSYCHIC",
              "move2": "SHADOW_BALL",
              "move3": "SUBMISSION",
              "move4": "ICE_PUNCH"
            }
          ]
        },
        {
          "name": "EliteFourKoga",
          "pokemon": [
            {
              "name": "VENOMOTH",
              "item": "BRIGHTPOWDER",
              "move1": "DOUBLE_TEAM",
              "move2": "TOXIC",
              "move3": "BATON_PASS",
              "move4": "PSYBEAM"
            },
            {
              "name": "MAGMAR",
              "item": "MAGNET",
              "move1": "DOUBLE_TEAM",
              "move2": "TOXIC",
              "move3": "CONFUSE_RAY",
              "move4": "FLAMETHROWER"
            },
            {
              "name": "LAPRAS",
              "item": "LEFTOVERS",
              "move1": "DOUBLE_TEAM",
              "move2": "TOXIC",
              "move3": "CONFUSE_RAY",
              "move4": "SURF"
            },
            {
              "name": "STANTLER",
              "item": "MYSTERYBERRY",
              "move1": "DOUBLE_TEAM",
              "move2": "TOXIC",
              "move3": "CONFUSE_RAY",
              "move4": "EARTHQUAKE"
            },
            {
              "name": "LANTURN",
              "item": "QUICK CLAW",
              "move1": "DOUBLE_TEAM",
              "move2": "TOXIC",
              "move3": "CONFUSE_RAY",
              "move4": "THUNDERBOLT"
            },
            {
              "name": "ARIADOS",
              "item": "FOCUS BAND",
              "move1": "DOUBLE_TEAM",
              "move2": "SPIDER_WEB",
              "move3": "BATON_PASS",
              "move4": "PSYBEAM"
            }
          ]
        },
        {
          "name": "EliteFourBruno",
          "pokemon": [
            {
              "name": "MACHAMP",
              "item": "QUICK CLAW",
              "move1": "CROSS_CHOP",
              "move2": "EARTHQUAKE",
              "move3": "ROCK_SLIDE",
              "move4": "FISSURE"
            },
            {
              "name": "GOLEM",
              "item": "BRIGHTPOWDER",
              "move1": "ROCK_SLIDE",
              "move2": "MAGNITUDE",
              "move3": "SUBMISSION",
              "move4": "FISSURE"
            },
            {
              "name": "PRIMEAPE",
              "item": "FOCUS BAND",
              "move1": "CROSS_CHOP",
              "move2": "ROCK_SLIDE",
              "move3": "REVERSAL",
              "move4": "COUNTER"
            },
            {
              "name": "GRANBULL",
              "item": "PRZCUREBERRY",
              "move1": "STRENGTH",
              "move2": "SHADOW_BALL",
              "move3": "SLUDGE_BOMB",
              "move4": "DYNAMIC_PUNCH"
            },
            {
              "name": "EXEGGUTOR",
              "item": "MAGNET",
              "move1": "GIGA_DRAIN",
              "move2": "PSYCHIC",
              "move3": "ANCIENT_POWER",
              "move4": "EXPLOSION"
            },
            {
              "name": "URSARING",
              "item": "SCOPE LENS",
              "move1": "SLASH",
              "move2": "EARTHQUAKE",
              "move3": "CRUNCH",
              "move4": "COUNTER"
            }
          ]
        },
        {
          "name": "EliteFourKaren",
          "pokemon": [
            {
              "name": "UMBREON",
              "item": "FOCUS BAND",
              "move1": "SWAGGER",
              "move2": "SCREECH",
              "move3": "FEINT_ATTACK",
              "move4": "PSYCHIC"
            },
            {
              "name": "PERSIAN",
              "item": "BRIGHTPOWDER",
              "move1": "SWAGGER",
              "move2": "SCREECH",
              "move3": "HEADBUTT",
              "move4": "SHADOW_BALL"
            },
            {
              "name": "MURKROW",
              "item": "SCOPE LENS",
              "move1": "SWAGGER",
              "move2": "MEAN_LOOK",
              "move3": "PSYCH_UP",
              "move4": "DRILL_PECK"
            },
            {
              "name": "SLOWBRO",
              "item": "QUICK CLAW",
              "move1": "SWAGGER",
              "move2": "THUNDER_WAVE",
              "move3": "SURF",
              "move4": "SUBMISSION"
            },
            {
              "name": "MISDREAVUS",
              "item": "MYSTERYBERRY",
              "move1": "MEAN_LOOK",
              "move2": "PERISH_SONG",
              "move3": "PAIN_SPLIT",
              "move4": "PSYCHIC"
            },
            {
              "name": "ELECTRODE",
              "item": "KING\u0027S ROCK",
              "move1": "SWAGGER",
              "move2": "THUNDER_WAVE",
              "move3": "HEADBUTT",
              "move4": "THUNDERBOLT"
            }
          ]
        }
      ]
    },
    {
      "name": "EliteFourChampion",
      "trainers": [
        {
          "name": "ChampionLance",
          "pokemon": [
            {
              "name": "DRAGONITE",
              "item": "SCOPE LENS",
              "move1": "DRAGON_BREATH",
              "move2": "ICE_BEAM",
              "move3": "THUNDERBOLT",
              "move4": "HYPER_BEAM"
            },
            {
              "name": "AERODACTYL",
              "item": "KING\u0027S ROCK",
              "move1": "ANCIENT_POWER",
              "move2": "WING_ATTACK",
              "move3": "EARTHQUAKE",
              "move4": "HYPER_BEAM"
            },
            {
              "name": "FERALIGATR",
              "item": "NONE",
              "move1": "SURF",
              "move2": "EARTHQUAKE",
              "move3": "BLIZZARD",
              "move4": "HYPER_BEAM"
            },
            {
              "name": "KANGASKHAN",
              "item": "BRIGHTPOWDER",
              "move1": "SUBMISSION",
              "move2": "EARTHQUAKE",
              "move3": "ROCK_SLIDE",
              "move4": "HYPER_BEAM"
            },
            {
              "name": "ARCANINE",
              "item": "MAGNET",
              "move1": "FLAMETHROWER",
              "move2": "EXTREME_SPEED",
              "move3": "CRUNCH",
              "move4": "HYPER_BEAM"
            },
            {
              "name": "TYRANITAR",
              "item": "QUICK CLAW",
              "move1": "CRUNCH",
              "move2": "ROCK_SLIDE",
              "move3": "EARTHQUAKE",
              "move4": "HYPER_BEAM"
            }
          ]
        }
      ]
    },
    {
      "name": "VermilionGym",
      "trainers": [
        {
          "name": "LeaderLt.Surge",
          "pokemon": [
            {
              "name": "RAICHU",
              "item": "FOCUS BAND",
              "move1": "THUNDERBOLT",
              "move2": "THUNDER_WAVE",
              "move3": "REVERSAL",
              "move4": "SURF"
            },
            {
              "name": "VICTREEBEL",
              "item": "MAGNET",
              "move1": "RAZOR_LEAF",
              "move2": "SLUDGE_BOMB",
              "move3": "BODY_SLAM",
              "move4": "STUN_SPORE"
            },
            {
              "name": "PORYGON2",
              "item": "QUICK CLAW",
              "move1": "CONVERSION_2",
              "move2": "TRI_ATTACK",
              "move3": "PSYCHIC",
              "move4": "BLIZZARD"
            },
            {
              "name": "QUAGSIRE",
              "item": "BRIGHTPOWDER",
              "move1": "SURF",
              "move2": "EARTHQUAKE",
              "move3": "ANCIENT_POWER",
              "move4": "ICE_BEAM"
            },
            {
              "name": "DODRIO",
              "item": "SCOPE LENS",
              "move1": "DRILL_PECK",
              "move2": "TRI_ATTACK",
              "move3": "PURSUIT",
              "move4": "STEEL_WING"
            },
            {
              "name": "JOLTEON",
              "item": "KING\u0027S ROCK",
              "move1": "THUNDERBOLT",
              "move2": "HIDDEN_POWER",
              "move3": "ROAR",
              "move4": "THUNDER_WAVE"
            }
          ]
        }
      ]
    },
    {
      "name": "SaffronGym",
      "trainers": [
        {
          "name": "LeaderSabrina",
          "pokemon": [
            {
              "name": "ALAKAZAM",
              "item": "KING\u0027S ROCK",
              "move1": "PSYCHIC",
              "move2": "THUNDER_PUNCH",
              "move3": "FIRE_PUNCH",
              "move4": "FUTURE_SIGHT"
            },
            {
              "name": "SCIZOR",
              "item": "MAGNET",
              "move1": "METAL_CLAW",
              "move2": "SLASH",
              "move3": "LIGHT_SCREEN",
              "move4": "REVERSAL"
            },
            {
              "name": "TYPHLOSION",
              "item": "FOCUS BAND",
              "move1": "FLAMETHROWER",
              "move2": "EARTHQUAKE",
              "move3": "THUNDER_PUNCH",
              "move4": "REVERSAL"
            },
            {
              "name": "HITMONLEE",
              "item": "SCOPE LENS",
              "move1": "DYNAMIC_PUNCH",
              "move2": "MEGA_KICK",
              "move3": "FORESIGHT",
              "move4": "MIND_READER"
            },
            {
              "name": "SANDSLASH",
              "item": "BRIGHTPOWDER",
              "move1": "EARTHQUAKE",
              "move2": "SLASH",
              "move3": "ROCK_SLIDE",
              "move4": "SUBMISSION"
            },
            {
              "name": "SLOWKING",
              "item": "QUICK CLAW",
              "move1": "PSYCHIC",
              "move2": "SURF",
              "move3": "EARTHQUAKE",
              "move4": "FUTURE_SIGHT"
            }
          ]
        }
      ]
    },
    {
      "name": "CeruleanGym",
      "trainers": [
        {
          "name": "LeaderMisty",
          "pokemon": [
            {
              "name": "STARMIE",
              "item": "KING\u0027S ROCK",
              "move1": "SURF",
              "move2": "PSYCHIC",
              "move3": "THUNDER",
              "move4": "RAIN_DANCE"
            },
            {
              "name": "WIGGLYTUFF",
              "item": "QUICK CLAW",
              "move1": "DOUBLE_EDGE",
              "move2": "ICE_BEAM",
              "move3": "THUNDER",
              "move4": "RAIN_DANCE"
            },
            {
              "name": "NIDOQUEEN",
              "item": "SCOPE LENS",
              "move1": "EARTHQUAKE",
              "move2": "SURF",
              "move3": "THUNDER",
              "move4": "RAIN_DANCE"
            },
            {
              "name": "AMPHAROS",
              "item": "BRIGHTPOWDER",
              "move1": "THUNDER",
              "move2": "LIGHT_SCREEN",
              "move3": "REFLECT",
              "move4": "RAIN_DANCE"
            },
            {
              "name": "DRAGONAIR",
              "item": "BITTER BERRY",
              "move1": "ICE_BEAM",
              "move2": "SURF",
              "move3": "THUNDER",
              "move4": "RAIN_DANCE"
            },
            {
              "name": "POLITOED",
              "item": "FOCUS BAND",
              "move1": "HYDRO_PUMP",
              "move2": "EARTHQUAKE",
              "move3": "ICE_BEAM",
              "move4": "RAIN_DANCE"
            }
          ]
        }
      ]
    },
    {
      "name": "CeladonGym",
      "trainers": [
        {
          "name": "LeaderErika",
          "pokemon": [
            {
              "name": "BELLOSSOM",
              "item": "QUICK CLAW",
              "move1": "RAZOR_LEAF",
              "move2": "RETURN",
              "move3": "SLEEP_POWDER",
              "move4": "STUN_SPORE"
            },
            {
              "name": "MAROWAK",
              "item": "THICK CLUB",
              "move1": "BONEMERANG",
              "move2": "BELLY_DRUM",
              "move3": "REST",
              "move4": "SNORE"
            },
            {
              "name": "NINETALES",
              "item": "BRIGHTPOWDER",
              "move1": "FLAMETHROWER",
              "move2": "BODY_SLAM",
              "move3": "IRON_TAIL",
              "move4": "HYPNOSIS"
            },
            {
              "name": "MANTINE",
              "item": "MINT BERRY",
              "move1": "SURF",
              "move2": "ICE_BEAM",
              "move3": "REST",
              "move4": "SLEEP_TALK"
            },
            {
              "name": "BLISSEY",
              "item": "MAGNET",
              "move1": "SING",
              "move2": "PSYCHIC",
              "move3": "REFLECT",
              "move4": "LIGHT_SCREEN"
            },
            {
              "name": "EXEGGUTOR",
              "item": "FOCUS BAND",
              "move1": "GIGA_DRAIN",
              "move2": "PSYCHIC",
              "move3": "SLEEP_POWDER",
              "move4": "STUN_SPORE"
            }
          ]
        }
      ]
    },
    {
      "name": "FuchsiaGym",
      "trainers": [
        {
          "name": "LeaderJanine",
          "pokemon": [
            {
              "name": "CROBAT",
              "item": "KING\u0027S ROCK",
              "move1": "CONFUSE_RAY",
              "move2": "MEAN_LOOK",
              "move3": "TOXIC",
              "move4": "BITE"
            },
            {
              "name": "MEGANIUM",
              "item": "QUICK CLAW",
              "move1": "ATTRACT",
              "move2": "TOXIC",
              "move3": "LEECH_SEED",
              "move4": "RAZOR_LEAF"
            },
            {
              "name": "MUK",
              "item": "FOCUS BAND",
              "move1": "SWAGGER",
              "move2": "MEAN_LOOK",
              "move3": "TOXIC",
              "move4": "FIRE_PUNCH"
            },
            {
              "name": "VAPOREON",
              "item": "BRIGHTPOWDER",
              "move1": "DOUBLE_TEAM",
              "move2": "BATON_PASS",
              "move3": "SURF",
              "move4": "ICE_BEAM"
            },
            {
              "name": "FORRETRESS",
              "item": "SCOPE LENS",
              "move1": "SWAGGER",
              "move2": "SPIKES",
              "move3": "SANDSTORM",
              "move4": "DOUBLE_EDGE"
            },
            {
              "name": "GIRAFARIG",
              "item": "MAGNET",
              "move1": "DOUBLE_TEAM",
              "move2": "BATON_PASS",
              "move3": "PSYCHIC",
              "move4": "CRUNCH"
            }
          ]
        }
      ]
    },
    {
      "name": "PewterGym",
      "trainers": [
        {
          "name": "LeaderBrock",
          "pokemon": [
            {
              "name": "STEELIX",
              "item": "SCOPE LENS",
              "move1": "ROCK_SLIDE",
              "move2": "EARTHQUAKE",
              "move3": "RETURN",
              "move4": "FISSURE"
            },
            {
              "name": "HERACROSS",
              "item": "FOCUS BAND",
              "move1": "MEGAHORN",
              "move2": "REVERSAL",
              "move3": "COUNTER",
              "move4": "EARTHQUAKE"
            },
            {
              "name": "RHYDON",
              "item": "QUICK CLAW",
              "move1": "ROCK_SLIDE",
              "move2": "EARTHQUAKE",
              "move3": "DOUBLE_EDGE",
              "move4": "FISSURE"
            },
            {
              "name": "SLOWBRO",
              "item": "BRIGHTPOWDER",
              "move1": "SURF",
              "move2": "PSYCHIC",
              "move3": "FLAMETHROWER",
              "move4": "FISSURE"
            },
            {
              "name": "URSARING",
              "item": "MINT BERRY",
              "move1": "DEFENSE_CURL",
              "move2": "ROLLOUT",
              "move3": "SLASH",
              "move4": "FOCUS_ENERGY"
            },
            {
              "name": "SHUCKLE",
              "item": "LEFTOVERS",
              "move1": "DEFENSE_CURL",
              "move2": "ROLLOUT",
              "move3": "SAFEGUARD",
              "move4": "WRAP"
            }
          ]
        }
      ]
    },
    {
      "name": "CinnabarGym",
      "trainers": [
        {
          "name": "LeaderBlaine",
          "pokemon": [
            {
              "name": "ARCANINE",
              "item": "KING\u0027S ROCK",
              "move1": "SUNNY_DAY",
              "move2": "FIRE_BLAST",
              "move3": "EXTREME_SPEED",
              "move4": "ROAR"
            },
            {
              "name": "MR.MIME",
              "item": "SCOPE LENS",
              "move1": "SUNNY_DAY",
              "move2": "FIRE_PUNCH",
              "move3": "SOLAR_BEAM",
              "move4": "PSYCHIC"
            },
            {
              "name": "CHANSEY",
              "item": "MAGNET",
              "move1": "SUNNY_DAY",
              "move2": "FIRE_BLAST",
              "move3": "SOLAR_BEAM",
              "move4": "COUNTER"
            },
            {
              "name": "CLEFABLE",
              "item": "FOCUS BAND",
              "move1": "SUNNY_DAY",
              "move2": "FIRE_BLAST",
              "move3": "SOLAR_BEAM",
              "move4": "MOONLIGHT"
            },
            {
              "name": "VILEPLUME",
              "item": "QUICK CLAW",
              "move1": "SUNNY_DAY",
              "move2": "SOLAR_BEAM",
              "move3": "SLUDGE_BOMB",
              "move4": "SYNTHESIS"
            },
            {
              "name": "MOLTRES",
              "item": "BRIGHTPOWDER",
              "move1": "SUNNY_DAY",
              "move2": "FIRE_BLAST",
              "move3": "WING_ATTACK",
              "move4": "STEEL_WING"
            }
          ]
        }
      ]
    },
    {
      "name": "ViridianGym",
      "trainers": [
        {
          "name": "LeaderBlue",
          "pokemon": [
            {
              "name": "SCYTHER",
              "item": "BRIGHTPOWDER",
              "move1": "SWORDS_DANCE",
              "move2": "AGILITY",
              "move3": "BATON_PASS",
              "move4": "WING_ATTACK"
            },
            {
              "name": "MILTANK",
              "item": "MAGNET",
              "move1": "BODY_SLAM",
              "move2": "EARTHQUAKE",
              "move3": "REVERSAL",
              "move4": "SHADOW_BALL"
            },
            {
              "name": "GENGAR",
              "item": "KING\u0027S ROCK",
              "move1": "PSYCHIC",
              "move2": "ICE_PUNCH",
              "move3": "FIRE_PUNCH",
              "move4": "THUNDERBOLT"
            },
            {
              "name": "HOUNDOOM",
              "item": "FOCUS BAND",
              "move1": "FLAMETHROWER",
              "move2": "CRUNCH",
              "move3": "IRON_TAIL",
              "move4": "REVERSAL"
            },
            {
              "name": "PILOSWINE",
              "item": "QUICK CLAW",
              "move1": "ICE_BEAM",
              "move2": "EARTHQUAKE",
              "move3": "ROCK_SLIDE",
              "move4": "ROAR"
            },
            {
              "name": "KINGDRA",
              "item": "SCOPE LENS",
              "move1": "SURF",
              "move2": "DRAGON_BREATH",
              "move3": "ICE_BEAM",
              "move4": "FLAIL"
            }
          ]
        }
      ]
    },
    {
      "name": "SilverCave",
      "trainers": [
        {
          "name": "red",
          "pokemon": [
            {
              "name": "RAIKOU",
              "item": "FOCUS BAND",
              "move1": "THUNDERBOLT",
              "move2": "BITE",
              "move3": "IRON_TAIL",
              "move4": "HIDDEN_POWER"
            },
            {
              "name": "ENTEI",
              "item": "SCOPE LENS",
              "move1": "FIRE_BLAST",
              "move2": "BITE",
              "move3": "IRON_TAIL",
              "move4": "HIDDEN_POWER"
            },
            {
              "name": "SUICUNE",
              "item": "BRIGHTPOWDER",
              "move1": "SURF",
              "move2": "ICE_BEAM",
              "move3": "ROAR",
              "move4": "HIDDEN_POWER"
            },
            {
              "name": "DRAGONITE",
              "item": "MAGNET",
              "move1": "FLY",
              "move2": "BODY_SLAM",
              "move3": "THUNDER_WAVE",
              "move4": "HIDDEN_POWER"
            },
            {
              "name": "SNORLAX",
              "item": "QUICK CLAW",
              "move1": "BODY_SLAM",
              "move2": "EARTHQUAKE",
              "move3": "SHADOW_BALL",
              "move4": "HIDDEN_POWER"
            },
            {
              "name": "ESPEON",
              "item": "KING\u0027S ROCK",
              "move1": "PSYCHIC",
              "move2": "BITE",
              "move3": "REFLECT",
              "move4": "HIDDEN_POWER"
            }
          ]
        }
      ]
    },
    {
      "name": "SecretCave",
      "trainers": [
        {
          "name": "rival",
          "pokemon": [
            {
              "name": "LUGIA",
              "item": "LEFTOVERS",
              "move1": "AEROBLAST",
              "move2": "EARTHQUAKE",
              "move3": "PSYCHIC",
              "move4": "SAFEGUARD"
            },
            {
              "name": "HO-OH",
              "item": "QUICK CLAW",
              "move1": "SACRED_FIRE",
              "move2": "THUNDER",
              "move3": "EARTHQUAKE",
              "move4": "GIGA_DRAIN"
            },
            {
              "name": "MEWTWO",
              "item": "KING\u0027S ROCK",
              "move1": "PSYCHIC",
              "move2": "SUBMISSION",
              "move3": "THUNDERBOLT",
              "move4": "RECOVER"
            }
          ]
        }
      ]
    }
  ]
}